gridnm/__init__.py
gridnm/gridnm.py
gridnm/py.typed
gridnm-1.0.1.dist-info/METADATA
gridnm-1.0.1.dist-info/WHEEL
gridnm-1.0.1.dist-info/licenses/LICENSE
gridnm-1.0.1.dist-info/RECORD
