Metadata-Version: 2.3
Name: gridnm
Version: 1.0.1
Summary: Grid-restrained Nelder-Mead algorithm
Project-URL: Homepage, https://github.com/mifauss/GridNM
Project-URL: Issues, https://github.com/mifauss/GridNM/issues
Author-email: Michael Fauss <mfauss@ets.org>
License-File: LICENSE
Classifier: License :: OSI Approved :: MIT License
Classifier: Operating System :: OS Independent
Classifier: Programming Language :: Python :: 3
Requires-Python: >=3.10
Requires-Dist: numpy
Requires-Dist: scipy
Provides-Extra: tests
Requires-Dist: pytest; extra == 'tests'
